praisonai_tools/__init__.py
praisonai_tools/cli.py
praisonai_tools/docs_generator/README.md
praisonai_tools/docs_generator/__init__.py
praisonai_tools/docs_generator/__main__.py
praisonai_tools/docs_generator/generator.py
praisonai_tools/fcp_tool/__init__.py
praisonai_tools/fcp_tool/cli.py
praisonai_tools/fcp_tool/commandpost.py
praisonai_tools/fcp_tool/doctor.py
praisonai_tools/fcp_tool/fcpxml.py
praisonai_tools/fcp_tool/injector.py
praisonai_tools/fcp_tool/intent.py
praisonai_tools/fcp_tool/prompting.py
praisonai_tools/observability/__init__.py
praisonai_tools/observability/base.py
praisonai_tools/observability/config.py
praisonai_tools/observability/manager.py
praisonai_tools/observability/providers/__init__.py
praisonai_tools/observability/providers/agentops_provider.py
praisonai_tools/observability/providers/arize_phoenix_provider.py
praisonai_tools/observability/providers/atla_provider.py
praisonai_tools/observability/providers/braintrust_provider.py
praisonai_tools/observability/providers/datadog_provider.py
praisonai_tools/observability/providers/langdb_provider.py
praisonai_tools/observability/providers/langfuse_provider.py
praisonai_tools/observability/providers/langsmith_provider.py
praisonai_tools/observability/providers/langtrace_provider.py
praisonai_tools/observability/providers/langwatch_provider.py
praisonai_tools/observability/providers/maxim_provider.py
praisonai_tools/observability/providers/mlflow_provider.py
praisonai_tools/observability/providers/neatlogs_provider.py
praisonai_tools/observability/providers/openlit_provider.py
praisonai_tools/observability/providers/opik_provider.py
praisonai_tools/observability/providers/patronus_provider.py
praisonai_tools/observability/providers/portkey_provider.py
praisonai_tools/observability/providers/traceloop_provider.py
praisonai_tools/observability/providers/truefoundry_provider.py
praisonai_tools/observability/providers/weave_provider.py
praisonai_tools/recipe_tools/__init__.py
praisonai_tools-0.2.14.dist-info/METADATA
praisonai_tools-0.2.14.dist-info/WHEEL
praisonai_tools-0.2.14.dist-info/entry_points.txt
praisonai_tools-0.2.14.dist-info/licenses/LICENSE
praisonai_tools-0.2.14.dist-info/RECORD
