Metadata-Version: 2.4
Name: praisonai-tools
Version: 0.2.14
Summary: Extended tools for PraisonAI Agents
Project-URL: Homepage, https://docs.praison.ai
Project-URL: Repository, https://github.com/MervinPraison/PraisonAI-Tools
Project-URL: Documentation, https://docs.praison.ai/tools
Project-URL: Issues, https://github.com/MervinPraison/PraisonAI-Tools/issues
Author: Mervin Praison
License: MIT
License-File: LICENSE
Keywords: agents,ai,custom-tools,plugin,praisonai,tools
Classifier: Development Status :: 4 - Beta
Classifier: Intended Audience :: Developers
Classifier: License :: OSI Approved :: MIT License
Classifier: Programming Language :: Python :: 3
Classifier: Programming Language :: Python :: 3.10
Classifier: Programming Language :: Python :: 3.11
Classifier: Programming Language :: Python :: 3.12
Classifier: Topic :: Scientific/Engineering :: Artificial Intelligence
Classifier: Topic :: Software Development :: Libraries :: Python Modules
Requires-Python: >=3.10
Requires-Dist: praisonaiagents>=0.0.1
Provides-Extra: dev
Requires-Dist: pytest-asyncio>=0.23.0; extra == 'dev'
Requires-Dist: pytest>=8.0.0; extra == 'dev'
Provides-Extra: wordpress
Requires-Dist: praisonaiwp[ai]>=0.1.0; extra == 'wordpress'
